[
  { "name": "Aabidah", "gender": "Girl", "meaning": "Worshipper", "origin": "Arabic" },
  { "name": "Aabish", "gender": "Girl", "meaning": "Daughter of Sa'ad", "origin": "Arabic" },
  { "name": "Aadil", "gender": "Boy", "meaning": "Just, Upright", "origin": "Arabic" },
  { "name": "Aafia", "gender": "Girl", "meaning": "Health, vitality", "origin": "Urdu" },
  { "name": "Aakif", "gender": "Boy", "meaning": "Devoted", "origin": "Arabic" },
  { "name": "Aalamgir", "gender": "Boy", "meaning": "Conqueror of the world", "origin": "Urdu" },
  { "name": "Aaquib", "gender": "Boy", "meaning": "Follower", "origin": "Arabic" },
  { "name": "Aarib", "gender": "Boy", "meaning": "Healthy", "origin": "Arabic" },
  { "name": "Aashif", "gender": "Boy", "meaning": "Bold", "origin": "Arabic" },
  { "name": "Aasir", "gender": "Boy", "meaning": "Captivating", "origin": "Arabic" },
  { "name": "Aatikah", "gender": "Girl", "meaning": "Generous", "origin": "Arabic" },
  { "name": "Abad", "gender": "Boy", "meaning": "Eternity", "origin": "Arabic" },
  { "name": "Abadah", "gender": "Boy", "meaning": "Worshipper", "origin": "Arabic" },
  { "name": "Abbas", "gender": "Boy", "meaning": "Lion", "origin": "Arabic" },
  { "name": "Abdaal", "gender": "Boy", "meaning": "Devotee", "origin": "Arabic" },
  { "name": "Abdul-Ahad", "gender": "Boy", "meaning": "Servant of the One", "origin": "Arabic" },
  { "name": "Abdul-Ali", "gender": "Boy", "meaning": "Servant of the Most High", "origin": "Arabic" },
  { "name": "Abdul-Azim", "gender": "Boy", "meaning": "Servant of the Mighty", "origin": "Arabic" },
  { "name": "Abdul-Baqi", "gender": "Boy", "meaning": "Servant of the Everlasting", "origin": "Arabic" },
  { "name": "Abdul-Bari", "gender": "Boy", "meaning": "Servant of the Creator", "origin": "Arabic" },
  { "name": "Abdul-Basit", "gender": "Boy", "meaning": "Servant of the Extender", "origin": "Arabic" },
  { "name": "Abdul-Ghaffar", "gender": "Boy", "meaning": "Servant of the Forgiver", "origin": "Arabic" },
  { "name": "Abdul-Ghafur", "gender": "Boy", "meaning": "Servant of the Forgiving", "origin": "Arabic" },
  { "name": "Abdul-Hadi", "gender": "Boy", "meaning": "Servant of the Guide", "origin": "Arabic" },
  { "name": "Abdul-Hafiz", "gender": "Boy", "meaning": "Servant of the Protector", "origin": "Arabic" },
  { "name": "Abdul-Hai", "gender": "Boy", "meaning": "Servant of the Living", "origin": "Arabic" },
  { "name": "Abdul-Hakim", "gender": "Boy", "meaning": "Servant of the Wise", "origin": "Arabic" },
  { "name": "Abdul-Halim", "gender": "Boy", "meaning": "Servant of the Forbearing", "origin": "Arabic" },
  { "name": "Abdul-Hamid", "gender": "Boy", "meaning": "Servant of the Praiseworthy", "origin": "Arabic" },
  { "name": "Abdul-Haq", "gender": "Boy", "meaning": "Servant of the Truth", "origin": "Arabic" },
  { "name": "Abdul-Hasib", "gender": "Boy", "meaning": "Servant of the Reckoner", "origin": "Arabic" },
  { "name": "Abdul-Jabbar", "gender": "Boy", "meaning": "Servant of the Compeller", "origin": "Arabic" },
  { "name": "Abdul-Jalil", "gender": "Boy", "meaning": "Servant of the Majestic", "origin": "Arabic" },
  { "name": "Abdul-Karim", "gender": "Boy", "meaning": "Servant of the Noble", "origin": "Arabic" },
  { "name": "Abdul-Latif", "gender": "Boy", "meaning": "Servant of the Subtle One", "origin": "Arabic" },
  { "name": "Abdul-Majid", "gender": "Boy", "meaning": "Servant of the Glorious", "origin": "Arabic" },
  { "name": "Abdul-Malik", "gender": "Boy", "meaning": "Servant of the King", "origin": "Arabic" },
  { "name": "Abdul-Matin", "gender": "Boy", "meaning": "Servant of the Strong", "origin": "Arabic" },
  { "name": "Abdul-Muiz", "gender": "Boy", "meaning": "Servant of the Giver of Honor", "origin": "Arabic" },
  { "name": "Abdul-Mujib", "gender": "Boy", "meaning": "Servant of the Responder", "origin": "Arabic" },
  { "name": "Abdul-Nasser", "gender": "Boy", "meaning": "Servant of the Helper", "origin": "Arabic" },
  { "name": "Abdul-Qadir", "gender": "Boy", "meaning": "Servant of the Capable", "origin": "Arabic" },
  { "name": "Abdul-Qayyum", "gender": "Boy", "meaning": "Servant of the Self-Subsisting", "origin": "Arabic" },
  { "name": "Abdul-Quddus", "gender": "Boy", "meaning": "Servant of the Holy", "origin": "Arabic" },
  { "name": "Abdul-Rauf", "gender": "Boy", "meaning": "Servant of the Kind", "origin": "Arabic" },
  { "name": "Abdul-Razzaq", "gender": "Boy", "meaning": "Servant of the Provider", "origin": "Arabic" },
  { "name": "Abdul-Salam", "gender": "Boy", "meaning": "Servant of Peace", "origin": "Arabic" },
  { "name": "Abdul-Samad", "gender": "Boy", "meaning": "Servant of the Eternal", "origin": "Arabic" },
  { "name": "Abdul-Wahab", "gender": "Boy", "meaning": "Servant of the Bestower", "origin": "Arabic" },
  { "name": "Abdul-Wahid", "gender": "Boy", "meaning": "Servant of the One", "origin": "Arabic" },
  { "name": "Abdur-Rahim", "gender": "Boy", "meaning": "Servant of the Merciful", "origin": "Arabic" },
  { "name": "Abdur-Rahman", "gender": "Boy", "meaning": "Servant of the Beneficent", "origin": "Arabic" },
  { "name": "Abdus-Sabur", "gender": "Boy", "meaning": "Servant of the Patient", "origin": "Arabic" },
  { "name": "Abdus-Sami", "gender": "Boy", "meaning": "Servant of the All-Hearing", "origin": "Arabic" },
  { "name": "Abdus-Sattar", "gender": "Boy", "meaning": "Servant of the Veiler", "origin": "Arabic" },
  { "name": "Abidullah", "gender": "Boy", "meaning": "Worshipper of Allah", "origin": "Arabic" },
  { "name": "Abisali", "gender": "Boy", "meaning": "Warrior in Islam", "origin": "Arabic" },
  { "name": "Aboubacar", "gender": "Boy", "meaning": "Abu Bakr (West African)", "origin": "African" },
  { "name": "Abraar", "gender": "Boy", "meaning": "Righteous", "origin": "Arabic" },
  { "name": "Abu", "gender": "Boy", "meaning": "Father of", "origin": "Arabic" },
  { "name": "Abubakr", "gender": "Boy", "meaning": "Father of the young camel", "origin": "Arabic" },
  { "name": "Abul-Fazl", "gender": "Boy", "meaning": "Father of Grace", "origin": "Arabic" },
  { "name": "Abul-Hasan", "gender": "Boy", "meaning": "Father of Hasan", "origin": "Arabic" },
  { "name": "Abul-Khair", "gender": "Boy", "meaning": "Father of Goodness", "origin": "Arabic" },
  { "name": "Adam", "gender": "Boy", "meaning": "Man; Earth", "origin": "Quranic" },
  { "name": "Adara", "gender": "Girl", "meaning": "Virgin", "origin": "Arabic" },
  { "name": "Adawiyah", "gender": "Girl", "meaning": "Plant (Summer plant)", "origin": "Arabic" },
  { "name": "Adeeba", "gender": "Girl", "meaning": "Literary woman", "origin": "Urdu" },
  { "name": "Adeem", "gender": "Boy", "meaning": "Rare", "origin": "Arabic" },
  { "name": "Adham", "gender": "Boy", "meaning": "Black", "origin": "Arabic" },
  { "name": "Adib", "gender": "Boy", "meaning": "Writer", "origin": "Arabic" },
  { "name": "Adilah", "gender": "Girl", "meaning": "Just", "origin": "Arabic" },
  { "name": "Adina", "gender": "Girl", "meaning": "Pious", "origin": "Arabic" },
  { "name": "Adl", "gender": "Boy", "meaning": "Justice", "origin": "Arabic" },
  { "name": "Adnan", "gender": "Boy", "meaning": "Settler", "origin": "Arabic" },
  { "name": "Adria", "gender": "Girl", "meaning": "Wealthy", "origin": "Arabic" },
  { "name": "Afaf", "gender": "Girl", "meaning": "Chastity", "origin": "Arabic" },
  { "name": "Afif", "gender": "Boy", "meaning": "Chaste", "origin": "Arabic" },
  { "name": "Afifa", "gender": "Girl", "meaning": "Chaste", "origin": "Arabic" },
  { "name": "Afiya", "gender": "Girl", "meaning": "Health", "origin": "Swahili" },
  { "name": "Afra", "gender": "Girl", "meaning": "Dust colored", "origin": "Arabic" },
  { "name": "Afrah", "gender": "Girl", "meaning": "Happiness", "origin": "Arabic" },
  { "name": "Afshan", "gender": "Girl", "meaning": "Sprinkled", "origin": "Persian" },
  { "name": "Afya", "gender": "Girl", "meaning": "Health", "origin": "Arabic" },
  { "name": "Afza", "gender": "Girl", "meaning": "Augmenting", "origin": "Arabic" },
  { "name": "Afzal", "gender": "Boy", "meaning": "Better", "origin": "Arabic" },
  { "name": "Ahad", "gender": "Boy", "meaning": "One", "origin": "Arabic" },
  { "name": "Ahmad", "gender": "Boy", "meaning": "Praised", "origin": "Arabic" },
  { "name": "Ahsan", "gender": "Boy", "meaning": "Excellence", "origin": "Arabic" },
  { "name": "Ahtisham", "gender": "Boy", "meaning": "Modesty", "origin": "Urdu" },
  { "name": "Aida", "gender": "Girl", "meaning": "Visiting", "origin": "Arabic" },
  { "name": "Aigul", "gender": "Girl", "meaning": "Moon flower", "origin": "Kazakh/Turkic" },
  { "name": "Aiman", "gender": "Unisex", "meaning": "Right hand", "origin": "Arabic" },
  { "name": "Ainat", "gender": "Girl", "meaning": "Woman with large eyes", "origin": "Arabic" },
  { "name": "Aisatou", "gender": "Girl", "meaning": "Aisha (West African)", "origin": "African" },
  { "name": "Aisha", "gender": "Girl", "meaning": "Alive", "origin": "Arabic" },
  { "name": "Aiya", "gender": "Girl", "meaning": "Miracle", "origin": "Arabic" },
  { "name": "Ajlan", "gender": "Boy", "meaning": "Haste", "origin": "Arabic" },
  { "name": "Ajmal", "gender": "Boy", "meaning": "Beautiful", "origin": "Arabic" },
  { "name": "Akbar", "gender": "Boy", "meaning": "Greatest", "origin": "Arabic" },
  { "name": "Akhtar", "gender": "Unisex", "meaning": "Star", "origin": "Persian" },
  { "name": "Akif", "gender": "Boy", "meaning": "Devoted", "origin": "Arabic" },
  { "name": "Akil", "gender": "Boy", "meaning": "Wise", "origin": "Arabic" },
  { "name": "Akilah", "gender": "Girl", "meaning": "Intelligent", "origin": "Arabic" },
  { "name": "Akram", "gender": "Boy", "meaning": "Generous", "origin": "Arabic" },
  { "name": "Ala", "gender": "Boy", "meaning": "Nobility", "origin": "Arabic" },
  { "name": "Aladdin", "gender": "Boy", "meaning": "Glory of faith", "origin": "Arabic" },
  { "name": "Alam", "gender": "Boy", "meaning": "World", "origin": "Arabic" },
  { "name": "Alamgir", "gender": "Boy", "meaning": "World Conqueror", "origin": "Urdu" },
  { "name": "Alauddin", "gender": "Boy", "meaning": "Excellence of Religion", "origin": "Arabic" },
  { "name": "Aleem", "gender": "Boy", "meaning": "Knowledgeable", "origin": "Arabic" },
  { "name": "Aleena", "gender": "Girl", "meaning": "Soft", "origin": "Urdu" },
  { "name": "Alhassan", "gender": "Boy", "meaning": "The handsome", "origin": "African" },
  { "name": "Ali", "gender": "Boy", "meaning": "High", "origin": "Arabic" },
  { "name": "Alia", "gender": "Girl", "meaning": "Exalted", "origin": "Arabic" },
  { "name": "Alim", "gender": "Boy", "meaning": "Scholar", "origin": "Arabic" },
  { "name": "Alina", "gender": "Girl", "meaning": "Bright", "origin": "Arabic" },
  { "name": "Aliya", "gender": "Girl", "meaning": "High status", "origin": "Arabic" },
  { "name": "Aliyah", "gender": "Girl", "meaning": "Exalted", "origin": "Arabic" },
  { "name": "Almas", "gender": "Unisex", "meaning": "Diamond", "origin": "Arabic" },
  { "name": "Almir", "gender": "Boy", "meaning": "Prince", "origin": "Urdu" },
  { "name": "Altaf", "gender": "Boy", "meaning": "Kindness", "origin": "Arabic" },
  { "name": "Alvina", "gender": "Girl", "meaning": "Friend", "origin": "Urdu" },
  { "name": "Amad", "gender": "Boy", "meaning": "Pillar", "origin": "Arabic" },
  { "name": "Amal", "gender": "Unisex", "meaning": "Hope", "origin": "Arabic" },
  { "name": "Aman", "gender": "Boy", "meaning": "Peace", "origin": "Arabic" },
  { "name": "Amani", "gender": "Girl", "meaning": "Wishes", "origin": "Arabic" },
  { "name": "Amara", "gender": "Girl", "meaning": "Eternal", "origin": "Arabic" },
  { "name": "Amatullah", "gender": "Girl", "meaning": "Servant of Allah", "origin": "Arabic" },
  { "name": "Ambar", "gender": "Girl", "meaning": "Amber", "origin": "Arabic" },
  { "name": "Ameen", "gender": "Boy", "meaning": "Trustworthy", "origin": "Arabic" },
  { "name": "Ameer", "gender": "Boy", "meaning": "Prince", "origin": "Arabic" },
  { "name": "Ameera", "gender": "Girl", "meaning": "Princess", "origin": "Arabic" },
  { "name": "Amel", "gender": "Girl", "meaning": "Hope", "origin": "Arabic" },
  { "name": "Amid", "gender": "Boy", "meaning": "Leader", "origin": "Arabic" },
  { "name": "Amin", "gender": "Boy", "meaning": "Faithful", "origin": "Arabic" },
  { "name": "Amina", "gender": "Girl", "meaning": "Trustworthy", "origin": "Arabic" },
  { "name": "Amir", "gender": "Boy", "meaning": "Prince", "origin": "Arabic" },
  { "name": "Amira", "gender": "Girl", "meaning": "Princess", "origin": "Arabic" },
  { "name": "Amjad", "gender": "Boy", "meaning": "More glorious", "origin": "Arabic" },
  { "name": "Ammar", "gender": "Boy", "meaning": "Long lived", "origin": "Arabic" },
  { "name": "Amna", "gender": "Girl", "meaning": "Peace", "origin": "Arabic" },
  { "name": "Amr", "gender": "Boy", "meaning": "Life", "origin": "Arabic" },
  { "name": "Amra", "gender": "Girl", "meaning": "Long life", "origin": "Arabic" },
  { "name": "Anam", "gender": "Girl", "meaning": "Creatures", "origin": "Arabic" },
  { "name": "Anan", "gender": "Unisex", "meaning": "Clouds", "origin": "Arabic" },
  { "name": "Anas", "gender": "Boy", "meaning": "Affection", "origin": "Arabic" },
  { "name": "Anaya", "gender": "Girl", "meaning": "Care", "origin": "Arabic" },
  { "name": "Anbar", "gender": "Girl", "meaning": "Fragrance", "origin": "Arabic" },
  { "name": "Anees", "gender": "Boy", "meaning": "Companion", "origin": "Arabic" },
  { "name": "Anika", "gender": "Girl", "meaning": "Grace", "origin": "Arabic" },
  { "name": "Aniq", "gender": "Boy", "meaning": "Neat", "origin": "Arabic" },
  { "name": "Anis", "gender": "Boy", "meaning": "Friend", "origin": "Arabic" },
  { "name": "Anisa", "gender": "Girl", "meaning": "Friendly", "origin": "Arabic" },
  { "name": "Anjum", "gender": "Unisex", "meaning": "Stars", "origin": "Urdu" },
  { "name": "Ansar", "gender": "Boy", "meaning": "Helpers", "origin": "Arabic" },
  { "name": "Antar", "gender": "Boy", "meaning": "Hero", "origin": "Arabic" },
  { "name": "Anum", "gender": "Girl", "meaning": "Blessing", "origin": "Urdu" },
  { "name": "Anwar", "gender": "Boy", "meaning": "Lights", "origin": "Arabic" },
  { "name": "Anwara", "gender": "Girl", "meaning": "Ray of Light", "origin": "Arabic" },
  { "name": "Aqdas", "gender": "Unisex", "meaning": "Holy", "origin": "Arabic" },
  { "name": "Aqeel", "gender": "Boy", "meaning": "Wise", "origin": "Arabic" },
  { "name": "Aqib", "gender": "Boy", "meaning": "Successor", "origin": "Arabic" },
  { "name": "Aqil", "gender": "Boy", "meaning": "Wise", "origin": "Arabic" },
  { "name": "Aqila", "gender": "Girl", "meaning": "Wise", "origin": "Arabic" },
  { "name": "Aqsa", "gender": "Girl", "meaning": "Farthest", "origin": "Arabic" },
  { "name": "Ara", "gender": "Girl", "meaning": "Adorning", "origin": "Arabic" },
  { "name": "Arafat", "gender": "Boy", "meaning": "Mount Arafat", "origin": "Arabic" },
  { "name": "Areeb", "gender": "Boy", "meaning": "Skillful", "origin": "Arabic" },
  { "name": "Areeba", "gender": "Girl", "meaning": "Wise", "origin": "Urdu" },
  { "name": "Areej", "gender": "Girl", "meaning": "Fragrance", "origin": "Arabic" },
  { "name": "Arfa", "gender": "Girl", "meaning": "Greatness", "origin": "Arabic" },
  { "name": "Arfan", "gender": "Boy", "meaning": "Gratitude", "origin": "Arabic" },
  { "name": "Arham", "gender": "Boy", "meaning": "Merciful", "origin": "Arabic" },
  { "name": "Arib", "gender": "Boy", "meaning": "Wise", "origin": "Arabic" },
  { "name": "Ariba", "gender": "Girl", "meaning": "Wise", "origin": "Arabic" },
  { "name": "Arif", "gender": "Boy", "meaning": "Knowing", "origin": "Arabic" },
  { "name": "Arifa", "gender": "Girl", "meaning": "Learned", "origin": "Arabic" },
  { "name": "Arij", "gender": "Girl", "meaning": "Sweet Smell", "origin": "Arabic" },
  { "name": "Arish", "gender": "Boy", "meaning": "Righteous", "origin": "Arabic" },
  { "name": "Arisha", "gender": "Girl", "meaning": "Highness", "origin": "Arabic" },
  { "name": "Arman", "gender": "Boy", "meaning": "Wish", "origin": "Persian" },
  { "name": "Arqam", "gender": "Boy", "meaning": "Writer", "origin": "Arabic" },
  { "name": "Arsal", "gender": "Boy", "meaning": "Messenger", "origin": "Arabic" },
  { "name": "Arsalan", "gender": "Boy", "meaning": "Lion", "origin": "Persian" },
  { "name": "Arshad", "gender": "Boy", "meaning": "Guided", "origin": "Arabic" },
  { "name": "Arshi", "gender": "Girl", "meaning": "Of the Throne", "origin": "Arabic" },
  { "name": "Arwa", "gender": "Girl", "meaning": "Gracefulness", "origin": "Arabic" },
  { "name": "Aryan", "gender": "Boy", "meaning": "Warrior", "origin": "Arabic" },
  { "name": "Arzo", "gender": "Girl", "meaning": "Wish", "origin": "Persian" },
  { "name": "Asad", "gender": "Boy", "meaning": "Lion", "origin": "Arabic" },
  { "name": "Asal", "gender": "Girl", "meaning": "Honey", "origin": "Arabic" },
  { "name": "Asar", "gender": "Boy", "meaning": "Mark", "origin": "Arabic" },
  { "name": "Asbah", "gender": "Girl", "meaning": "Pure", "origin": "Arabic" },
  { "name": "Aseel", "gender": "Unisex", "meaning": "Genuine", "origin": "Arabic" },
  { "name": "Aseela", "gender": "Girl", "meaning": "Noble", "origin": "Arabic" },
  { "name": "Asfa", "gender": "Girl", "meaning": "Pure", "origin": "Arabic" },
  { "name": "Asghar", "gender": "Boy", "meaning": "Smaller", "origin": "Arabic" },
  { "name": "Ashar", "gender": "Boy", "meaning": "Wise", "origin": "Arabic" },
  { "name": "Ashfaq", "gender": "Boy", "meaning": "Compassion", "origin": "Arabic" },
  { "name": "Ashiq", "gender": "Boy", "meaning": "Lover", "origin": "Arabic" },
  { "name": "Ashraf", "gender": "Boy", "meaning": "Honorable", "origin": "Arabic" },
  { "name": "Asif", "gender": "Boy", "meaning": "Forgiveness", "origin": "Arabic" },
  { "name": "Asifa", "gender": "Girl", "meaning": "Organizer", "origin": "Arabic" },
  { "name": "Asil", "gender": "Boy", "meaning": "Noble", "origin": "Arabic" },
  { "name": "Asim", "gender": "Boy", "meaning": "Protector", "origin": "Arabic" },
  { "name": "Asima", "gender": "Girl", "meaning": "Protector", "origin": "Arabic" },
  { "name": "Asiya", "gender": "Girl", "meaning": "Pharaoh's Wife", "origin": "Quranic" },
  { "name": "Aslam", "gender": "Boy", "meaning": "Safer", "origin": "Arabic" },
  { "name": "Asma", "gender": "Girl", "meaning": "Exalted", "origin": "Arabic" },
  { "name": "Asmara", "gender": "Girl", "meaning": "Butterfly", "origin": "Arabic" },
  { "name": "Asra", "gender": "Girl", "meaning": "Night travel", "origin": "Arabic" },
  { "name": "Asrar", "gender": "Unisex", "meaning": "Secrets", "origin": "Arabic" },
  { "name": "Aswad", "gender": "Boy", "meaning": "Black", "origin": "Arabic" },
  { "name": "Asya", "gender": "Girl", "meaning": "Grace", "origin": "Arabic" },
  { "name": "Ata", "gender": "Boy", "meaning": "Gift", "origin": "Arabic" },
  { "name": "Ateeb", "gender": "Boy", "meaning": "Pious", "origin": "Arabic" },
  { "name": "Ateeq", "gender": "Boy", "meaning": "Ancient", "origin": "Arabic" },
  { "name": "Athar", "gender": "Boy", "meaning": "Pure", "origin": "Arabic" },
  { "name": "Atheer", "gender": "Boy", "meaning": "Favored", "origin": "Arabic" },
  { "name": "Atif", "gender": "Boy", "meaning": "Kind", "origin": "Arabic" },
  { "name": "Atifa", "gender": "Girl", "meaning": "Affectionate", "origin": "Arabic" },
  { "name": "Atik", "gender": "Boy", "meaning": "Ancient", "origin": "Arabic" },
  { "name": "Atika", "gender": "Girl", "meaning": "Pure", "origin": "Arabic" },
  { "name": "Atiq", "gender": "Boy", "meaning": "Ancient", "origin": "Arabic" },
  { "name": "Atiya", "gender": "Girl", "meaning": "Gift", "origin": "Arabic" },
  { "name": "Atta", "gender": "Boy", "meaning": "Gift", "origin": "Arabic" },
  { "name": "Auf", "gender": "Boy", "meaning": "Lion", "origin": "Arabic" },
  { "name": "Aun", "gender": "Boy", "meaning": "Help", "origin": "Arabic" },
  { "name": "Aus", "gender": "Boy", "meaning": "Wolf", "origin": "Arabic" },
  { "name": "Ausaf", "gender": "Boy", "meaning": "Virtues", "origin": "Arabic" },
  { "name": "Awa", "gender": "Girl", "meaning": "Angel", "origin": "Arabic" },
  { "name": "Awad", "gender": "Boy", "meaning": "Reward", "origin": "Arabic" },
  { "name": "Awais", "gender": "Boy", "meaning": "Wolf", "origin": "Arabic" },
  { "name": "Awan", "gender": "Boy", "meaning": "Moment", "origin": "Arabic" },
  { "name": "Aws", "gender": "Boy", "meaning": "Gift", "origin": "Arabic" },
  { "name": "Awwab", "gender": "Boy", "meaning": "Repentant", "origin": "Arabic" },
  { "name": "Awwal", "gender": "Boy", "meaning": "First", "origin": "Arabic" },
  { "name": "Aya", "gender": "Girl", "meaning": "Verse", "origin": "Arabic" },
  { "name": "Ayaan", "gender": "Boy", "meaning": "God's gift", "origin": "Arabic" },
  { "name": "Ayah", "gender": "Girl", "meaning": "Sign", "origin": "Arabic" },
  { "name": "Ayana", "gender": "Girl", "meaning": "Flower", "origin": "Urdu" },
  { "name": "Ayat", "gender": "Girl", "meaning": "Verses", "origin": "Arabic" },
  { "name": "Ayaz", "gender": "Boy", "meaning": "Night breeze", "origin": "Persian" },
  { "name": "Aydin", "gender": "Boy", "meaning": "Enlightened", "origin": "Turkish" },
  { "name": "Ayesha", "gender": "Girl", "meaning": "Alive", "origin": "Arabic" },
  { "name": "Ayham", "gender": "Boy", "meaning": "Brave", "origin": "Arabic" },
  { "name": "Ayla", "gender": "Girl", "meaning": "Moonlight", "origin": "Turkish" },
  { "name": "Ayman", "gender": "Boy", "meaning": "Lucky", "origin": "Arabic" },
  { "name": "Ayn", "gender": "Unisex", "meaning": "Eye", "origin": "Arabic" },
  { "name": "Aynur", "gender": "Girl", "meaning": "Moonlight", "origin": "Turkic" },
  { "name": "Ayra", "gender": "Girl", "meaning": "Respectable", "origin": "Arabic" },
  { "name": "Ayser", "gender": "Boy", "meaning": "Easy", "origin": "Arabic" },
  { "name": "Aysha", "gender": "Girl", "meaning": "Alive", "origin": "Arabic" },
  { "name": "Ayub", "gender": "Boy", "meaning": "Job", "origin": "Arabic" },
  { "name": "Ayzal", "gender": "Girl", "meaning": "Gift", "origin": "Arabic" },
  { "name": "Aza", "gender": "Girl", "meaning": "Comfort", "origin": "Arabic" },
  { "name": "Azad", "gender": "Boy", "meaning": "Free", "origin": "Persian" },
  { "name": "Azal", "gender": "Boy", "meaning": "Eternity", "origin": "Arabic" },
  { "name": "Azam", "gender": "Boy", "meaning": "Greatest", "origin": "Arabic" },
  { "name": "Azan", "gender": "Boy", "meaning": "Call to prayer", "origin": "Arabic" },
  { "name": "Azar", "gender": "Boy", "meaning": "Fire", "origin": "Persian" },
  { "name": "Azeem", "gender": "Boy", "meaning": "Great", "origin": "Arabic" },
  { "name": "Azeema", "gender": "Girl", "meaning": "Great", "origin": "Arabic" },
  { "name": "Azfer", "gender": "Boy", "meaning": "Leader", "origin": "Arabic" },
  { "name": "Azhar", "gender": "Boy", "meaning": "Luminous", "origin": "Arabic" },
  { "name": "Azheen", "gender": "Boy", "meaning": "Beautiful", "origin": "Persian" },
  { "name": "Azib", "gender": "Boy", "meaning": "Bachelor", "origin": "Arabic" },
  { "name": "Azim", "gender": "Boy", "meaning": "Protector", "origin": "Arabic" },
  { "name": "Aziz", "gender": "Boy", "meaning": "Powerful", "origin": "Arabic" },
  { "name": "Aziza", "gender": "Girl", "meaning": "Precious", "origin": "Arabic" },
  { "name": "Azka", "gender": "Girl", "meaning": "Pious", "origin": "Arabic" },
  { "name": "Azlan", "gender": "Boy", "meaning": "Lion", "origin": "Turkish" },
  { "name": "Azli", "gender": "Boy", "meaning": "From beginning", "origin": "Arabic" },
  { "name": "Azma", "gender": "Girl", "meaning": "Blessing", "origin": "Arabic" },
  { "name": "Azmat", "gender": "Unisex", "meaning": "Respect", "origin": "Arabic" },
  { "name": "Azmeer", "gender": "Boy", "meaning": "Clever", "origin": "Arabic" },
  { "name": "Azmi", "gender": "Boy", "meaning": "Determination", "origin": "Arabic" },
  { "name": "Azmina", "gender": "Girl", "meaning": "Times", "origin": "Arabic" },
  { "name": "Azra", "gender": "Girl", "meaning": "Virgin", "origin": "Arabic" },
  { "name": "Azraf", "gender": "Boy", "meaning": "Elegant", "origin": "Arabic" },
  { "name": "Azraq", "gender": "Boy", "meaning": "Blue", "origin": "Arabic" },
  { "name": "Azraqi", "gender": "Boy", "meaning": "Authority", "origin": "Arabic" },
  { "name": "Azud", "gender": "Boy", "meaning": "Strength", "origin": "Arabic" },
  { "name": "Azwer", "gender": "Boy", "meaning": "Leader", "origin": "Arabic" },
  { "name": "Azzam", "gender": "Boy", "meaning": "Determined", "origin": "Arabic" },
  { "name": "Azzan", "gender": "Boy", "meaning": "Call to prayer", "origin": "Arabic" },
  { "name": "Baari", "gender": "Boy", "meaning": "Creator", "origin": "Arabic" },
  { "name": "Baasim", "gender": "Boy", "meaning": "Smiling", "origin": "Arabic" },
  { "name": "Baasima", "gender": "Girl", "meaning": "Smiling", "origin": "Arabic" },
  { "name": "Badar", "gender": "Boy", "meaning": "Full moon", "origin": "Arabic" },
  { "name": "Badi", "gender": "Boy", "meaning": "Wonderful", "origin": "Arabic" },
  { "name": "Badia", "gender": "Girl", "meaning": "Unique", "origin": "Arabic" },
  { "name": "Badiha", "gender": "Girl", "meaning": "Insight", "origin": "Arabic" },
  { "name": "Badiya", "gender": "Girl", "meaning": "Countryside", "origin": "Arabic" },
  { "name": "Badra", "gender": "Girl", "meaning": "Full moon", "origin": "Arabic" },
  { "name": "Badri", "gender": "Boy", "meaning": "Of full moon", "origin": "Arabic" },
  { "name": "Badriya", "gender": "Girl", "meaning": "Resembling moon", "origin": "Arabic" },
  { "name": "Badruddin", "gender": "Boy", "meaning": "Moon of faith", "origin": "Arabic" },
  { "name": "Badrunnisa", "gender": "Girl", "meaning": "Moon of women", "origin": "Arabic" },
  { "name": "Baha", "gender": "Boy", "meaning": "Glory", "origin": "Arabic" },
  { "name": "Bahauddin", "gender": "Boy", "meaning": "Glory of Faith", "origin": "Arabic" },
  { "name": "Bahadur", "gender": "Boy", "meaning": "Brave", "origin": "Turkish" },
  { "name": "Bahar", "gender": "Unisex", "meaning": "Spring", "origin": "Persian" },
  { "name": "Bahia", "gender": "Girl", "meaning": "Nice", "origin": "Arabic" },
  { "name": "Bahij", "gender": "Boy", "meaning": "Cheerful", "origin": "Arabic" },
  { "name": "Bahija", "gender": "Girl", "meaning": "Happy", "origin": "Arabic" },
  { "name": "Bahir", "gender": "Boy", "meaning": "Dazzling", "origin": "Arabic" },
  { "name": "Bahira", "gender": "Girl", "meaning": "Dazzling", "origin": "Arabic" },
  { "name": "Bahiya", "gender": "Girl", "meaning": "Beautiful", "origin": "Arabic" },
  { "name": "Bahjat", "gender": "Boy", "meaning": "Splendors", "origin": "Arabic" },
  { "name": "Bahman", "gender": "Boy", "meaning": "Well-spirited", "origin": "Persian" },
  { "name": "Bahoz", "gender": "Boy", "meaning": "Storm", "origin": "Kurdish" },
  { "name": "Bahram", "gender": "Boy", "meaning": "Victory", "origin": "Persian" },
  { "name": "Bahri", "gender": "Boy", "meaning": "Naval", "origin": "Arabic" },
  { "name": "Baiza", "gender": "Girl", "meaning": "White", "origin": "Arabic" },
  { "name": "Bajila", "gender": "Girl", "meaning": "Dignified", "origin": "Arabic" },
  { "name": "Bakht", "gender": "Unisex", "meaning": "Luck", "origin": "Persian" },
  { "name": "Bakhtawar", "gender": "Unisex", "meaning": "Lucky", "origin": "Persian" },
  { "name": "Bakhtiyar", "gender": "Boy", "meaning": "Lucky", "origin": "Persian" },
  { "name": "Bakir", "gender": "Boy", "meaning": "Early", "origin": "Arabic" },
  { "name": "Bakr", "gender": "Boy", "meaning": "Young camel", "origin": "Arabic" },
  { "name": "Balagh", "gender": "Boy", "meaning": "Message", "origin": "Arabic" },
  { "name": "Baleeg", "gender": "Boy", "meaning": "Eloquent", "origin": "Arabic" },
  { "name": "Baligh", "gender": "Boy", "meaning": "Eloquent", "origin": "Arabic" },
  { "name": "Balqis", "gender": "Girl", "meaning": "Queen of Sheba", "origin": "Arabic" },
  { "name": "Balsam", "gender": "Unisex", "meaning": "Remedy", "origin": "Arabic" },
  { "name": "Bana", "gender": "Girl", "meaning": "Tree type", "origin": "Arabic" },
  { "name": "Banafsha", "gender": "Girl", "meaning": "Violet", "origin": "Persian" },
  { "name": "Banan", "gender": "Girl", "meaning": "Fingertips", "origin": "Arabic" },
  { "name": "Banin", "gender": "Boy", "meaning": "Wise", "origin": "Arabic" },
  { "name": "Bano", "gender": "Girl", "meaning": "Lady", "origin": "Persian" },
  { "name": "Baqi", "gender": "Boy", "meaning": "Eternal", "origin": "Arabic" },
  { "name": "Baqir", "gender": "Boy", "meaning": "Genius", "origin": "Arabic" },
  { "name": "Bara", "gender": "Boy", "meaning": "Innocence", "origin": "Arabic" },
  { "name": "Baraa", "gender": "Boy", "meaning": "Innocent", "origin": "Arabic" },
  { "name": "Barah", "gender": "Girl", "meaning": "Innocence", "origin": "Arabic" },
  { "name": "Baraka", "gender": "Boy", "meaning": "Blessing", "origin": "Arabic" },
  { "name": "Barakah", "gender": "Unisex", "meaning": "Blessing", "origin": "Arabic" },
  { "name": "Barat", "gender": "Boy", "meaning": "Warrant", "origin": "Arabic" },
  { "name": "Bareea", "gender": "Girl", "meaning": "Innocent", "origin": "Arabic" },
  { "name": "Baria", "gender": "Girl", "meaning": "Excelling", "origin": "Arabic" },
  { "name": "Bariah", "gender": "Girl", "meaning": "Excelling", "origin": "Arabic" },
  { "name": "Barik", "gender": "Boy", "meaning": "Shining", "origin": "Arabic" },
  { "name": "Barin", "gender": "Unisex", "meaning": "Lofty", "origin": "Persian" },
  { "name": "Barir", "gender": "Boy", "meaning": "Faithful", "origin": "Arabic" },
  { "name": "Barirah", "gender": "Girl", "meaning": "Faithful", "origin": "Arabic" },
  { "name": "Barkat", "gender": "Boy", "meaning": "Blessings", "origin": "Arabic" },
  { "name": "Barkatullah", "gender": "Boy", "meaning": "Blessing of Allah", "origin": "Arabic" },
  { "name": "Barq", "gender": "Boy", "meaning": "Lightning", "origin": "Arabic" },
  { "name": "Barra", "gender": "Girl", "meaning": "Pious", "origin": "Arabic" },
  { "name": "Barraq", "gender": "Boy", "meaning": "Shining", "origin": "Arabic" },
  { "name": "Barzin", "gender": "Boy", "meaning": "Daring", "origin": "Persian" },
  { "name": "Basayel", "gender": "Boy", "meaning": "Brave", "origin": "Arabic" },
  { "name": "Baseem", "gender": "Boy", "meaning": "Smiling", "origin": "Arabic" },
  { "name": "Baseer", "gender": "Boy", "meaning": "Visionary", "origin": "Arabic" },
  { "name": "Baseera", "gender": "Girl", "meaning": "Wisdom", "origin": "Arabic" },
  { "name": "Baseerat", "gender": "Girl", "meaning": "Insight", "origin": "Arabic" },
  { "name": "Basha", "gender": "Boy", "meaning": "King", "origin": "Turkish" },
  { "name": "Bashaar", "gender": "Boy", "meaning": "Bringer of news", "origin": "Arabic" },
  { "name": "Bashair", "gender": "Girl", "meaning": "Good news", "origin": "Arabic" },
  { "name": "Bashar", "gender": "Boy", "meaning": "Human", "origin": "Arabic" },
  { "name": "Basharat", "gender": "Unisex", "meaning": "Good news", "origin": "Arabic" },
  { "name": "Basheera", "gender": "Girl", "meaning": "Bringer of news", "origin": "Arabic" },
  { "name": "Bashir", "gender": "Boy", "meaning": "Bringer of news", "origin": "Arabic" },
  { "name": "Bashira", "gender": "Girl", "meaning": "Joyful", "origin": "Arabic" },
  { "name": "Basil", "gender": "Boy", "meaning": "Brave", "origin": "Arabic" },
  { "name": "Basila", "gender": "Girl", "meaning": "Brave", "origin": "Arabic" },
  { "name": "Basim", "gender": "Boy", "meaning": "Smiling", "origin": "Arabic" },
  { "name": "Basima", "gender": "Girl", "meaning": "Smiling", "origin": "Arabic" },
  { "name": "Basir", "gender": "Boy", "meaning": "All-seeing", "origin": "Arabic" },
  { "name": "Basira", "gender": "Girl", "meaning": "Sagacious", "origin": "Arabic" },
  { "name": "Basit", "gender": "Boy", "meaning": "Extender", "origin": "Arabic" },
  { "name": "Basma", "gender": "Girl", "meaning": "Smile", "origin": "Arabic" },
  { "name": "Basmah", "gender": "Girl", "meaning": "Smile", "origin": "Arabic" },
  { "name": "Bassam", "gender": "Boy", "meaning": "Always smiling", "origin": "Arabic" },
  { "name": "Batin", "gender": "Boy", "meaning": "Inward", "origin": "Arabic" },
  { "name": "Batool", "gender": "Girl", "meaning": "Ascetic", "origin": "Arabic" },
  { "name": "Batul", "gender": "Girl", "meaning": "Virgin", "origin": "Arabic" },
  { "name": "Batuhan", "gender": "Boy", "meaning": "Strong ruler", "origin": "Turkish" },
  { "name": "Bayan", "gender": "Unisex", "meaning": "Eloquence", "origin": "Arabic" },
  { "name": "Bayhas", "gender": "Boy", "meaning": "Courageous", "origin": "Arabic" },
  { "name": "Baysan", "gender": "Girl", "meaning": "Pride", "origin": "Arabic" },
  { "name": "Baz", "gender": "Boy", "meaning": "Falcon", "origin": "Arabic" },
  { "name": "Bazla", "gender": "Girl", "meaning": "Generous", "origin": "Arabic" },
  { "name": "Beena", "gender": "Girl", "meaning": "Seeing", "origin": "Persian" },
  { "name": "Begum", "gender": "Girl", "meaning": "Lady", "origin": "Turkish" },
  { "name": "Behjat", "gender": "Unisex", "meaning": "Joy", "origin": "Arabic" },
  { "name": "Behnam", "gender": "Boy", "meaning": "Reputable", "origin": "Persian" },
  { "name": "Behram", "gender": "Boy", "meaning": "Mars", "origin": "Persian" },
  { "name": "Behrooz", "gender": "Boy", "meaning": "Good day", "origin": "Persian" },
  { "name": "Behrouz", "gender": "Boy", "meaning": "Lucky", "origin": "Persian" },
  { "name": "Behzad", "gender": "Boy", "meaning": "Noble", "origin": "Persian" },
  { "name": "Belal", "gender": "Boy", "meaning": "Water", "origin": "Arabic" },
  { "name": "Benazir", "gender": "Girl", "meaning": "Incomparable", "origin": "Persian" },
  { "name": "Berin", "gender": "Girl", "meaning": "Best", "origin": "Turkish" },
  { "name": "Beyza", "gender": "Girl", "meaning": "White", "origin": "Turkish" },
  { "name": "Beza", "gender": "Boy", "meaning": "White", "origin": "Arabic" },
  { "name": "Bhadur", "gender": "Boy", "meaning": "Brave", "origin": "Turkish" },
  { "name": "Bhai", "gender": "Boy", "meaning": "Brother", "origin": "Urdu" },
  { "name": "Bi", "gender": "Girl", "meaning": "Lady", "origin": "Urdu" },
  { "name": "Bibi", "gender": "Girl", "meaning": "Lady", "origin": "Persian" },
  { "name": "Bilal", "gender": "Boy", "meaning": "First Muezzin", "origin": "Arabic" },
  { "name": "Bilqis", "gender": "Girl", "meaning": "Queen", "origin": "Arabic" },
  { "name": "Bina", "gender": "Girl", "meaning": "Vision", "origin": "Persian" },
  { "name": "Binish", "gender": "Girl", "meaning": "Vision", "origin": "Persian" },
  { "name": "Bint", "gender": "Girl", "meaning": "Daughter", "origin": "Arabic" },
  { "name": "Binyamin", "gender": "Boy", "meaning": "Benjamin", "origin": "Arabic" },
  { "name": "Birrah", "gender": "Girl", "meaning": "Good deed", "origin": "Arabic" },
  { "name": "Bishr", "gender": "Boy", "meaning": "Joy", "origin": "Arabic" },
  { "name": "Bisma", "gender": "Girl", "meaning": "Smile", "origin": "Urdu" },
  { "name": "Bismal", "gender": "Girl", "meaning": "Fragrance", "origin": "Urdu" },
  { "name": "Bisman", "gender": "Girl", "meaning": "Polite", "origin": "Persian" },
  { "name": "Bita", "gender": "Girl", "meaning": "Unique", "origin": "Persian" },
  { "name": "Boman", "gender": "Boy", "meaning": "Great mind", "origin": "Persian" },
  { "name": "Bora", "gender": "Boy", "meaning": "Storm", "origin": "Turkish" },
  { "name": "Boran", "gender": "Boy", "meaning": "Thunderstorm", "origin": "Turkish" },
  { "name": "Bostan", "gender": "Unisex", "meaning": "Garden", "origin": "Persian" },
  { "name": "Boulus", "gender": "Boy", "meaning": "Paul", "origin": "Arabic" },
  { "name": "Bouran", "gender": "Girl", "meaning": "Cold wind", "origin": "Arabic" },
  { "name": "Bozorg", "gender": "Boy", "meaning": "Great", "origin": "Persian" },
  { "name": "Brahim", "gender": "Boy", "meaning": "Ibrahim", "origin": "Arabic" },
  { "name": "Budur", "gender": "Girl", "meaning": "Full moons", "origin": "Arabic" },
  { "name": "Buhairah", "gender": "Girl", "meaning": "Small lake", "origin": "Arabic" },
  { "name": "Buhaysah", "gender": "Girl", "meaning": "Walking with pride", "origin": "Arabic" },
  { "name": "Buhayyah", "gender": "Girl", "meaning": "Beautiful", "origin": "Arabic" },
  { "name": "Bujair", "gender": "Boy", "meaning": "Companion", "origin": "Arabic" },
  { "name": "Bukayr", "gender": "Boy", "meaning": "Early morning", "origin": "Arabic" },
  { "name": "Bukhari", "gender": "Boy", "meaning": "Imam Bukhari", "origin": "Persian" },
  { "name": "Bulbul", "gender": "Unisex", "meaning": "Nightingale", "origin": "Arabic" },
  { "name": "Bulqis", "gender": "Girl", "meaning": "Queen", "origin": "Arabic" },
  { "name": "Bulut", "gender": "Boy", "meaning": "Cloud", "origin": "Turkish" },
  { "name": "Bunyamin", "gender": "Boy", "meaning": "Benjamin", "origin": "Arabic" },
  { "name": "Burhanuddin", "gender": "Boy", "meaning": "Proof of Faith", "origin": "Arabic" },
  { "name": "Buri", "gender": "Boy", "meaning": "Excellent person", "origin": "Arabic" },
  { "name": "Burum", "gender": "Boy", "meaning": "Bud", "origin": "Arabic" },
  { "name": "Burzin", "gender": "Boy", "meaning": "Exalted", "origin": "Persian" },
  { "name": "Busayrah", "gender": "Girl", "meaning": "Insight", "origin": "Arabic" },
  { "name": "Bushr", "gender": "Boy", "meaning": "Joy", "origin": "Arabic" },
  { "name": "Bushra", "gender": "Girl", "meaning": "Good news", "origin": "Arabic" },
  { "name": "Busr", "gender": "Boy", "meaning": "Unripened dates", "origin": "Arabic" },
  { "name": "Buthayna", "gender": "Girl", "meaning": "Soft sand", "origin": "Arabic" },
  { "name": "Butrus", "gender": "Boy", "meaning": "Peter", "origin": "Arabic" },
  { "name": "Buzurg", "gender": "Boy", "meaning": "Great", "origin": "Persian" },
  { "name": "Cafer", "gender": "Boy", "meaning": "Stream", "origin": "Turkish" },
  { "name": "Cahit", "gender": "Boy", "meaning": "Hardworking", "origin": "Turkish" },
  { "name": "Cairo", "gender": "Boy", "meaning": "Victorious", "origin": "Arabic" },
  { "name": "Caleb", "gender": "Boy", "meaning": "Faithful", "origin": "Arabic" },
  { "name": "Can", "gender": "Boy", "meaning": "Life", "origin": "Turkish" },
  { "name": "Canan", "gender": "Girl", "meaning": "Beloved", "origin": "Turkish" },
  { "name": "Candan", "gender": "Unisex", "meaning": "Sincere", "origin": "Turkish" },
  { "name": "Cansel", "gender": "Girl", "meaning": "Flood of life", "origin": "Turkish" },
  { "name": "Cansu", "gender": "Girl", "meaning": "Water of life", "origin": "Turkish" },
  { "name": "Cavia", "gender": "Girl", "meaning": "Poem", "origin": "Urdu" },
  { "name": "Cavid", "gender": "Boy", "meaning": "Eternal", "origin": "Turkish" },
  { "name": "Cayla", "gender": "Girl", "meaning": "Castle", "origin": "Arabic" },
  { "name": "Cebrail", "gender": "Boy", "meaning": "Gabriel", "origin": "Turkish" },
  { "name": "Celal", "gender": "Boy", "meaning": "Glory", "origin": "Turkish" },
  { "name": "Celil", "gender": "Boy", "meaning": "Great", "origin": "Turkish" },
  { "name": "Cem", "gender": "Boy", "meaning": "King", "origin": "Turkish" },
  { "name": "Cemal", "gender": "Boy", "meaning": "Beauty", "origin": "Turkish" },
  { "name": "Cemil", "gender": "Boy", "meaning": "Beautiful", "origin": "Turkish" },
  { "name": "Cemile", "gender": "Girl", "meaning": "Beautiful", "origin": "Turkish" },
  { "name": "Cennet", "gender": "Girl", "meaning": "Paradise", "origin": "Turkish" },
  { "name": "Cevat", "gender": "Boy", "meaning": "Generous", "origin": "Turkish" },
  { "name": "Ceyda", "gender": "Girl", "meaning": "Good", "origin": "Turkish" },
  { "name": "Ceyhun", "gender": "Boy", "meaning": "River", "origin": "Turkish" },
  { "name": "Ceylan", "gender": "Girl", "meaning": "Gazelle", "origin": "Turkish" },
  { "name": "Cezmi", "gender": "Boy", "meaning": "Resolute", "origin": "Turkish" },
  { "name": "Chafia", "gender": "Girl", "meaning": "Healer", "origin": "Arabic" },
  { "name": "Chafik", "gender": "Boy", "meaning": "Compassionate", "origin": "Arabic" },
  { "name": "Chakir", "gender": "Boy", "meaning": "Thankful", "origin": "Arabic" },
  { "name": "Chaman", "gender": "Unisex", "meaning": "Garden", "origin": "Persian" },
  { "name": "Chamanara", "gender": "Girl", "meaning": "Adorning", "origin": "Persian" },
  { "name": "Chand", "gender": "Unisex", "meaning": "Moon", "origin": "Urdu" },
  { "name": "Chanda", "gender": "Girl", "meaning": "Moonlight", "origin": "Urdu" },
  { "name": "Chandni", "gender": "Girl", "meaning": "Moonlight", "origin": "Urdu" },
  { "name": "Changez", "gender": "Boy", "meaning": "Brave", "origin": "Mongol" },
  { "name": "Charagh", "gender": "Boy", "meaning": "Lamp", "origin": "Persian" },
  { "name": "Chawdhury", "gender": "Boy", "meaning": "Land owner", "origin": "Sanskrit" },
  { "name": "Chehra", "gender": "Girl", "meaning": "Face", "origin": "Persian" },
  { "name": "Chessy", "gender": "Girl", "meaning": "Peaceful", "origin": "Persian" },
  { "name": "Chiragh", "gender": "Boy", "meaning": "Lamp", "origin": "Persian" },
  { "name": "Choudhry", "gender": "Boy", "meaning": "Leader", "origin": "Urdu" },
  { "name": "Cihad", "gender": "Boy", "meaning": "Struggle", "origin": "Turkish" },
  { "name": "Cihan", "gender": "Unisex", "meaning": "World", "origin": "Turkish" },
  { "name": "Cihangir", "gender": "Boy", "meaning": "Conqueror", "origin": "Turkish" },
  { "name": "Civan", "gender": "Boy", "meaning": "Young", "origin": "Turkish" },
  { "name": "Cyra", "gender": "Girl", "meaning": "Moon-faced", "origin": "Persian" },
  { "name": "Cyrus", "gender": "Boy", "meaning": "Sun", "origin": "Persian" },
  { "name": "Daad", "gender": "Girl", "meaning": "Old name", "origin": "Arabic" },
  { "name": "Dabir", "gender": "Boy", "meaning": "Judge", "origin": "Persian" },
  { "name": "Daeem", "gender": "Boy", "meaning": "Eternal", "origin": "Arabic" },
  { "name": "Dafiyah", "gender": "Girl", "meaning": "Narrator", "origin": "Arabic" },
  { "name": "Dahab", "gender": "Girl", "meaning": "Gold", "origin": "Arabic" },
  { "name": "Dahma", "gender": "Girl", "meaning": "She-camel", "origin": "Arabic" },
  { "name": "Daiyan", "gender": "Boy", "meaning": "Ruler", "origin": "Arabic" },
  { "name": "Dakilah", "gender": "Girl", "meaning": "Country", "origin": "Arabic" },
  { "name": "Dalal", "gender": "Girl", "meaning": "Coquetry", "origin": "Arabic" },
  { "name": "Daleel", "gender": "Boy", "meaning": "Guide", "origin": "Arabic" },
  { "name": "Dalia", "gender": "Girl", "meaning": "Dahlia flower", "origin": "Arabic" },
  { "name": "Dalil", "gender": "Boy", "meaning": "Guide", "origin": "Arabic" },
  { "name": "Dalila", "gender": "Girl", "meaning": "Guide", "origin": "Arabic" },
  { "name": "Daliya", "gender": "Girl", "meaning": "Dahlia flower", "origin": "Arabic" },
  { "name": "Damir", "gender": "Boy", "meaning": "Heart", "origin": "Arabic" },
  { "name": "Damira", "gender": "Girl", "meaning": "Long lived", "origin": "Arabic" },
  { "name": "Dana", "gender": "Unisex", "meaning": "Wise", "origin": "Mixed" },
  { "name": "Daneen", "gender": "Girl", "meaning": "Princess", "origin": "Arabic" },
  { "name": "Dani", "gender": "Boy", "meaning": "Close", "origin": "Arabic" },
  { "name": "Dania", "gender": "Girl", "meaning": "Close", "origin": "Arabic" },
  { "name": "Danial", "gender": "Boy", "meaning": "Prophet Daniel", "origin": "Arabic" },
  { "name": "Danish", "gender": "Boy", "meaning": "Knowledge", "origin": "Persian" },
  { "name": "Daniya", "gender": "Girl", "meaning": "Kind hearted", "origin": "Arabic" },
  { "name": "Daniyal", "gender": "Boy", "meaning": "Intelligent", "origin": "Arabic" },
  { "name": "Dara", "gender": "Boy", "meaning": "Possessor", "origin": "Persian" },
  { "name": "Darakhshan", "gender": "Girl", "meaning": "Shining", "origin": "Persian" },
  { "name": "Daria", "gender": "Girl", "meaning": "Sea", "origin": "Persian" },
  { "name": "Darim", "gender": "Boy", "meaning": "Narrator", "origin": "Arabic" },
  { "name": "Daris", "gender": "Boy", "meaning": "Scholar", "origin": "Arabic" },
  { "name": "Darya", "gender": "Unisex", "meaning": "Sea", "origin": "Persian" },
  { "name": "Daud", "gender": "Boy", "meaning": "Beloved", "origin": "Arabic" },
  { "name": "Daulat", "gender": "Unisex", "meaning": "Wealth", "origin": "Arabic" },
  { "name": "Dawar", "gender": "Boy", "meaning": "Judge", "origin": "Arabic" },
  { "name": "Dawid", "gender": "Boy", "meaning": "Prince", "origin": "Arabic" },
  { "name": "Dawud", "gender": "Boy", "meaning": "Beloved", "origin": "Arabic" },
  { "name": "Deba", "gender": "Girl", "meaning": "Silk", "origin": "Persian" },
  { "name": "Deen", "gender": "Boy", "meaning": "Religion", "origin": "Arabic" },
  { "name": "Deena", "gender": "Girl", "meaning": "Obedience", "origin": "Arabic" },
  { "name": "Deenal", "gender": "Girl", "meaning": "Faith", "origin": "Arabic" },
  { "name": "Delara", "gender": "Girl", "meaning": "Adorning", "origin": "Persian" },
  { "name": "Delbar", "gender": "Girl", "meaning": "Sweetheart", "origin": "Persian" },
  { "name": "Delkash", "gender": "Girl", "meaning": "Fascinating", "origin": "Persian" },
  { "name": "Delruba", "gender": "Girl", "meaning": "Heart-ravishing", "origin": "Persian" },
  { "name": "Demir", "gender": "Boy", "meaning": "Iron", "origin": "Turkish" },
  { "name": "Deniz", "gender": "Unisex", "meaning": "Sea", "origin": "Turkish" },
  { "name": "Derya", "gender": "Unisex", "meaning": "Sea", "origin": "Turkish" },
  { "name": "Devlet", "gender": "Boy", "meaning": "State", "origin": "Turkish" },
  { "name": "Dhaakir", "gender": "Boy", "meaning": "One who praises", "origin": "Arabic" },
  { "name": "Dhakir", "gender": "Boy", "meaning": "One who remembers", "origin": "Arabic" },
  { "name": "Dhakirah", "gender": "Girl", "meaning": "One who remembers", "origin": "Arabic" },
  { "name": "Dhakiy", "gender": "Boy", "meaning": "Intelligent", "origin": "Arabic" },
  { "name": "Dhakiyah", "gender": "Girl", "meaning": "Intelligent", "origin": "Arabic" },
  { "name": "Dhakwan", "gender": "Boy", "meaning": "Intelligent", "origin": "Arabic" },
  { "name": "Dhameer", "gender": "Boy", "meaning": "Conscience", "origin": "Arabic" },
  { "name": "Dhiya", "gender": "Unisex", "meaning": "Light", "origin": "Arabic" },
  { "name": "Dhia", "gender": "Boy", "meaning": "Light", "origin": "Arabic" },
  { "name": "Dhuha", "gender": "Girl", "meaning": "Forenoon", "origin": "Arabic" },
  { "name": "Dhulfiqar", "gender": "Boy", "meaning": "Sword", "origin": "Arabic" },
  { "name": "Dhu", "gender": "Boy", "meaning": "Possessor", "origin": "Arabic" },
  { "name": "Diba", "gender": "Girl", "meaning": "Brocade", "origin": "Persian" },
  { "name": "Didar", "gender": "Girl", "meaning": "Vision", "origin": "Persian" },
  { "name": "Dihyah", "gender": "Boy", "meaning": "Commander", "origin": "Arabic" },
  { "name": "Dila", "gender": "Girl", "meaning": "Heart", "origin": "Persian" },
  { "name": "Dilara", "gender": "Girl", "meaning": "Beloved", "origin": "Persian" },
  { "name": "Dilawar", "gender": "Boy", "meaning": "Brave", "origin": "Persian" },
  { "name": "Dilbar", "gender": "Girl", "meaning": "Lover", "origin": "Persian" },
  { "name": "Dildar", "gender": "Boy", "meaning": "Charming", "origin": "Persian" },
  { "name": "Dilkash", "gender": "Girl", "meaning": "Attractive", "origin": "Persian" },
  { "name": "Dilruba", "gender": "Girl", "meaning": "Heart-ravishing", "origin": "Persian" },
  { "name": "Dilshad", "gender": "Unisex", "meaning": "Happy", "origin": "Persian" },
  { "name": "Dima", "gender": "Girl", "meaning": "Downpour", "origin": "Arabic" },
  { "name": "Dina", "gender": "Girl", "meaning": "Love", "origin": "Mixed" },
  { "name": "Dinar", "gender": "Unisex", "meaning": "Gold coin", "origin": "Arabic" },
  { "name": "Diya", "gender": "Unisex", "meaning": "Light", "origin": "Arabic" },
  { "name": "Diyari", "gender": "Boy", "meaning": "A gift", "origin": "Kurdish" },
  { "name": "Dizhwar", "gender": "Boy", "meaning": "Mean", "origin": "Kurdish" },
  { "name": "Doha", "gender": "Girl", "meaning": "Forenoon", "origin": "Arabic" },
  { "name": "Dolat", "gender": "Girl", "meaning": "Wealth", "origin": "Arabic" },
  { "name": "Dora", "gender": "Girl", "meaning": "Pearl", "origin": "Arabic" },
  { "name": "Dorar", "gender": "Girl", "meaning": "Pearls", "origin": "Arabic" },
  { "name": "Dost", "gender": "Boy", "meaning": "Friend", "origin": "Persian" },
  { "name": "Dostdar", "gender": "Boy", "meaning": "One who loves friends", "origin": "Persian" },
  { "name": "Douha", "gender": "Girl", "meaning": "Morning", "origin": "Arabic" },
  { "name": "Dounia", "gender": "Girl", "meaning": "The world", "origin": "Arabic" },
  { "name": "Du", "gender": "Girl", "meaning": "Pearl", "origin": "Arabic" },
  { "name": "Dua", "gender": "Girl", "meaning": "Prayer", "origin": "Arabic" },
  { "name": "Duaa", "gender": "Girl", "meaning": "Prayer", "origin": "Arabic" },
  { "name": "Duha", "gender": "Girl", "meaning": "Forenoon", "origin": "Arabic" },
  { "name": "Dujana", "gender": "Girl", "meaning": "Rain", "origin": "Arabic" },
  { "name": "Dunya", "gender": "Girl", "meaning": "World", "origin": "Arabic" },
  { "name": "Durdanah", "gender": "Girl", "meaning": "Pearl", "origin": "Persian" },
  { "name": "Durr", "gender": "Girl", "meaning": "Pearls", "origin": "Arabic" },
  { "name": "Durra", "gender": "Girl", "meaning": "Pearl", "origin": "Arabic" },
  { "name": "Durrah", "gender": "Girl", "meaning": "Large pearl", "origin": "Arabic" },
  { "name": "Durriya", "gender": "Girl", "meaning": "Sparkling", "origin": "Arabic" },
  { "name": "Durriyah", "gender": "Girl", "meaning": "Brilliant", "origin": "Arabic" },
  { "name": "Dzakir", "gender": "Boy", "meaning": "One who remembers", "origin": "Indonesian" },
  { "name": "Dzalikha", "gender": "Girl", "meaning": "Zuleikha", "origin": "Indonesian" },
  { "name": "Eaman", "gender": "Unisex", "meaning": "Faith", "origin": "Arabic" },
  { "name": "Eas", "gender": "Boy", "meaning": "Giving", "origin": "Arabic" },
  { "name": "Eashal", "gender": "Girl", "meaning": "Flower of Paradise", "origin": "Arabic" },
  { "name": "Eba", "gender": "Girl", "meaning": "Pride", "origin": "Arabic" },
  { "name": "Ebad", "gender": "Boy", "meaning": "Worshippers", "origin": "Arabic" },
  { "name": "Ebadat", "gender": "Unisex", "meaning": "Worship", "origin": "Persian" },
  { "name": "Ebi", "gender": "Boy", "meaning": "Paternal", "origin": "Persian" },
  { "name": "Ebrahim", "gender": "Boy", "meaning": "Father of multitudes", "origin": "Arabic" },
  { "name": "Ebru", "gender": "Girl", "meaning": "Cloud art", "origin": "Turkish" },
  { "name": "Ebtihal", "gender": "Girl", "meaning": "Supplication", "origin": "Arabic" },
  { "name": "Ebtisam", "gender": "Girl", "meaning": "Smiling", "origin": "Arabic" },
  { "name": "Ece", "gender": "Girl", "meaning": "Queen", "origin": "Turkish" },
  { "name": "Ecrin", "gender": "Girl", "meaning": "Reward", "origin": "Turkish" },
  { "name": "Edhem", "gender": "Boy", "meaning": "Dark", "origin": "Arabic" },
  { "name": "Edib", "gender": "Boy", "meaning": "Polite", "origin": "Turkish" },
  { "name": "Ediz", "gender": "Boy", "meaning": "High", "origin": "Turkish" },
  { "name": "Edra", "gender": "Girl", "meaning": "Power", "origin": "Arabic" },
  { "name": "Edris", "gender": "Boy", "meaning": "Prophet Idris", "origin": "Arabic" },
  { "name": "Efe", "gender": "Boy", "meaning": "Older brother", "origin": "Turkish" },
  { "name": "Effat", "gender": "Girl", "meaning": "Chastity", "origin": "Persian" },
  { "name": "Efrah", "gender": "Girl", "meaning": "Festival", "origin": "Arabic" },
  { "name": "Efsan", "gender": "Girl", "meaning": "Tale", "origin": "Turkish" },
  { "name": "Efthal", "gender": "Boy", "meaning": "Better", "origin": "Arabic" },
  { "name": "Ehab", "gender": "Boy", "meaning": "Gift", "origin": "Arabic" },
  { "name": "Ehan", "gender": "Boy", "meaning": "Full moon", "origin": "Arabic" },
  { "name": "Ehsan", "gender": "Unisex", "meaning": "Perfection", "origin": "Arabic" },
  { "name": "Ehtesham", "gender": "Boy", "meaning": "Modesty", "origin": "Arabic" },
  { "name": "Ehtiram", "gender": "Unisex", "meaning": "Honor", "origin": "Arabic" },
  { "name": "Eid", "gender": "Boy", "meaning": "Festivity", "origin": "Arabic" },
  { "name": "Eidam", "gender": "Boy", "meaning": "Determination", "origin": "Arabic" },
  { "name": "Eihab", "gender": "Boy", "meaning": "To give freely", "origin": "Arabic" },
  { "name": "Eiman", "gender": "Unisex", "meaning": "Faith", "origin": "Arabic" },
  { "name": "Eisa", "gender": "Boy", "meaning": "Jesus", "origin": "Arabic" },
  { "name": "Ejaz", "gender": "Boy", "meaning": "Miracle", "origin": "Arabic" },
  { "name": "Ejlaal", "gender": "Boy", "meaning": "To honor", "origin": "Arabic" },
  { "name": "Ekhlas", "gender": "Girl", "meaning": "Sincerity", "origin": "Arabic" },
  { "name": "Ekin", "gender": "Unisex", "meaning": "Harvest", "origin": "Turkish" },
  { "name": "Ekram", "gender": "Unisex", "meaning": "Honor", "origin": "Arabic" },
  { "name": "Ela", "gender": "Girl", "meaning": "Hazel", "origin": "Turkish" },
  { "name": "Elahi", "gender": "Boy", "meaning": "My God", "origin": "Arabic" },
  { "name": "Elan", "gender": "Boy", "meaning": "Announcement", "origin": "Arabic" },
  { "name": "Eldar", "gender": "Boy", "meaning": "Ruler", "origin": "Turkish" },
  { "name": "Elf", "gender": "Boy", "meaning": "Friend", "origin": "Turkish" },
  { "name": "Elham", "gender": "Girl", "meaning": "Inspiration", "origin": "Arabic" },
  { "name": "Elias", "gender": "Boy", "meaning": "Prophet Ilyas", "origin": "Arabic" },
  { "name": "Elif", "gender": "Girl", "meaning": "First letter", "origin": "Turkish" },
  { "name": "Elisha", "gender": "Boy", "meaning": "Prophet Al-Yasa", "origin": "Arabic" },
  { "name": "Eliza", "gender": "Girl", "meaning": "Unique", "origin": "Persian" },
  { "name": "Elma", "gender": "Girl", "meaning": "Apple", "origin": "Turkish" },
  { "name": "Elnaz", "gender": "Girl", "meaning": "Charm", "origin": "Persian" },
  { "name": "Elvan", "gender": "Girl", "meaning": "Colors", "origin": "Turkish" },
  { "name": "Emad", "gender": "Boy", "meaning": "Pillar", "origin": "Arabic" },
  { "name": "Emal", "gender": "Boy", "meaning": "Hope", "origin": "Arabic" },
  { "name": "Eman", "gender": "Girl", "meaning": "Faith", "origin": "Arabic" },
  { "name": "Emel", "gender": "Girl", "meaning": "Desire", "origin": "Turkish" },
  { "name": "Emil", "gender": "Boy", "meaning": "Friend", "origin": "Arabic" },
  { "name": "Emina", "gender": "Girl", "meaning": "Trustworthy", "origin": "Bosnian" },
  { "name": "Emir", "gender": "Boy", "meaning": "Prince", "origin": "Turkish" },
  { "name": "Emira", "gender": "Girl", "meaning": "Princess", "origin": "Turkish" },
  { "name": "Emna", "gender": "Girl", "meaning": "Safe", "origin": "Arabic" },
  { "name": "Emran", "gender": "Boy", "meaning": "Prosperity", "origin": "Arabic" },
  { "name": "Emre", "gender": "Boy", "meaning": "Friend", "origin": "Turkish" },
  { "name": "Enam", "gender": "Unisex", "meaning": "Gift", "origin": "Arabic" },
  { "name": "Enayat", "gender": "Boy", "meaning": "Grace", "origin": "Persian" },
  { "name": "Enis", "gender": "Boy", "meaning": "Friend", "origin": "Turkish" },
  { "name": "Enisa", "gender": "Girl", "meaning": "Good friend", "origin": "Turkish" },
  { "name": "Ensar", "gender": "Boy", "meaning": "Helpers", "origin": "Turkish" },
  { "name": "Enver", "gender": "Boy", "meaning": "Luminous", "origin": "Turkish" },
  { "name": "Eraj", "gender": "Boy", "meaning": "Morning light", "origin": "Persian" },
  { "name": "Eray", "gender": "Boy", "meaning": "First month", "origin": "Turkish" },
  { "name": "Erfan", "gender": "Boy", "meaning": "Knowledge", "origin": "Persian" },
  { "name": "Erhan", "gender": "Boy", "meaning": "Brave leader", "origin": "Turkish" },
  { "name": "Erina", "gender": "Girl", "meaning": "Beautiful lady", "origin": "Persian" },
  { "name": "Erol", "gender": "Boy", "meaning": "Brave", "origin": "Turkish" },
  { "name": "Erum", "gender": "Girl", "meaning": "Heaven", "origin": "Urdu" },
  { "name": "Esa", "gender": "Boy", "meaning": "Prophet Jesus", "origin": "Arabic" },
  { "name": "Esha", "gender": "Girl", "meaning": "Life", "origin": "Arabic" },
  { "name": "Eshaal", "gender": "Girl", "meaning": "Flower of Paradise", "origin": "Arabic" },
  { "name": "Eshal", "gender": "Girl", "meaning": "Name of a flower", "origin": "Urdu" },
  { "name": "Eshrat", "gender": "Unisex", "meaning": "Delight", "origin": "Persian" },
  { "name": "Esma", "gender": "Girl", "meaning": "Names", "origin": "Turkish" },
  { "name": "Esmail", "gender": "Boy", "meaning": "Prophet Ishmael", "origin": "Persian" },
  { "name": "Esmeray", "gender": "Girl", "meaning": "Dark moon", "origin": "Turkish" },
  { "name": "Esra", "gender": "Girl", "meaning": "Night journey", "origin": "Turkish" },
  { "name": "Essam", "gender": "Boy", "meaning": "Safeguard", "origin": "Arabic" },
  { "name": "Etem", "gender": "Boy", "meaning": "Perfect", "origin": "Turkish" },
  { "name": "Eti", "gender": "Girl", "meaning": "Gift", "origin": "Turkish" },
  { "name": "Etidal", "gender": "Unisex", "meaning": "Moderation", "origin": "Arabic" },
  { "name": "Evin", "gender": "Girl", "meaning": "Love", "origin": "Kurdish" },
  { "name": "Evren", "gender": "Unisex", "meaning": "Universe", "origin": "Turkish" },
  { "name": "Eyad", "gender": "Boy", "meaning": "Support", "origin": "Arabic" },
  { "name": "Eyla", "gender": "Girl", "meaning": "Oak tree", "origin": "Turkish" },
  { "name": "Eyman", "gender": "Boy", "meaning": "Blessed", "origin": "Turkish" },
  { "name": "Eyup", "gender": "Boy", "meaning": "Prophet Job", "origin": "Turkish" },
  { "name": "Ezel", "gender": "Unisex", "meaning": "Eternity", "origin": "Turkish" },
  { "name": "Ezra", "gender": "Boy", "meaning": "Prophet Ezra", "origin": "Arabic" },
  { "name": "Ezzah", "gender": "Girl", "meaning": "Honor", "origin": "Arabic" },
  { "name": "Ezzat", "gender": "Boy", "meaning": "Honor", "origin": "Persian" }
]
