[
  {
    "id": "ha71",
    "name": "Hababah",
    "gender": "Girl",
    "meaning": "A daughter of Ajlan; Narrator of Hadith",
    "origin": "Arabic",
    "verified": true
  },
  {
    "id": "ha1",
    "name": "Habib",
    "gender": "Boy",
    "meaning": "Beloved, friend",
    "origin": "Arabic",
    "verified": true
  },
  {
    "id": "ha2",
    "name": "Habiba",
    "gender": "Girl",
    "meaning": "Beloved, darling",
    "origin": "Arabic",
    "verified": true
  },
  {
    "id": "ha72",
    "name": "Habibah",
    "gender": "Girl",
    "meaning": "Beloved",
    "origin": "Arabic",
    "verified": true
  },
  {
    "id": "ha3",
    "name": "Habil",
    "gender": "Boy",
    "meaning": "Abel (Son of Adam)",
    "origin": "Quranic",
    "verified": true
  },
  {
    "id": "ha4",
    "name": "Hada",
    "gender": "Girl",
    "meaning": "Myrtle tree, guide",
    "origin": "Arabic",
    "verified": true
  },
  {
    "id": "ha73",
    "name": "Hadaya",
    "gender": "Girl",
    "meaning": "Gifts",
    "origin": "Arabic",
    "verified": true
  },
  {
    "id": "ha5",
    "name": "Hadeel",
    "gender": "Girl",
    "meaning": "Cooing of a pigeon",
    "origin": "Arabic",
    "verified": true
  },
  {
    "id": "ha74",
    "name": "Hadeel",
    "gender": "Girl",
    "meaning": "Cooing of pigeons",
    "origin": "Arabic",
    "verified": true
  },
  {
    "id": "ha75",
    "name": "Hadhirah",
    "gender": "Girl",
    "meaning": "Sweet smelling, smart",
    "origin": "Arabic",
    "verified": true
  },
  {
    "id": "ha6",
    "name": "Hadi",
    "gender": "Boy",
    "meaning": "Guide, leader",
    "origin": "Quranic",
    "verified": true
  },
  {
    "id": "ha7",
    "name": "Hadia",
    "gender": "Girl",
    "meaning": "Guide, gift",
    "origin": "Arabic",
    "verified": true
  },
  {
    "id": "ha8",
    "name": "Hadid",
    "gender": "Boy",
    "meaning": "Iron, sharp",
    "origin": "Quranic",
    "verified": true
  },
  {
    "id": "ha9",
    "name": "Hadiqa",
    "gender": "Girl",
    "meaning": "Garden, walled garden",
    "origin": "Arabic",
    "verified": true
  },
  {
    "id": "ha10",
    "name": "Hadiya",
    "gender": "Girl",
    "meaning": "Gift, present",
    "origin": "Arabic",
    "verified": true
  },
  {
    "id": "ha76",
    "name": "Hadiyah",
    "gender": "Girl",
    "meaning": "Guide to righteousness",
    "origin": "Arabic",
    "verified": true
  },
  {
    "id": "ha11",
    "name": "Hafeez",
    "gender": "Boy",
    "meaning": "Guardian, protector",
    "origin": "Quranic",
    "verified": true
  },
  {
    "id": "ha12",
    "name": "Hafiz",
    "gender": "Boy",
    "meaning": "Protector; One who memorized Quran",
    "origin": "Quranic",
    "verified": true
  },
  {
    "id": "ha77",
    "name": "Hafizah",
    "gender": "Girl",
    "meaning": "Guardian, protector",
    "origin": "Arabic",
    "verified": true
  },
  {
    "id": "ha13",
    "name": "Hafsa",
    "gender": "Girl",
    "meaning": "Cub (Young lioness); Wife of the Prophet",
    "origin": "Arabic",
    "verified": true
  },
  {
    "id": "ha78",
    "name": "Hafsah",
    "gender": "Girl",
    "meaning": "Wife of the Prophet (SAW)",
    "origin": "Arabic",
    "verified": true
  },
  {
    "id": "ha14",
    "name": "Haider",
    "gender": "Boy",
    "meaning": "Lion",
    "origin": "Arabic",
    "verified": true
  },
  {
    "id": "ha15",
    "name": "Haifa",
    "gender": "Girl",
    "meaning": "Slender, beautiful body",
    "origin": "Arabic",
    "verified": true
  },
  {
    "id": "ha79",
    "name": "Haifa",
    "gender": "Girl",
    "meaning": "Slender, of beautiful body",
    "origin": "Arabic",
    "verified": true
  },
  {
    "id": "ha16",
    "name": "Haimi",
    "gender": "Girl",
    "meaning": "Golden",
    "origin": "Sanskrit/Arabic usage",
    "verified": false
  },
  {
    "id": "ha17",
    "name": "Hajar",
    "gender": "Girl",
    "meaning": "Hagar (Wife of Ibrahim)",
    "origin": "Quranic",
    "verified": true
  },
  {
    "id": "ha80",
    "name": "Hajar",
    "gender": "Girl",
    "meaning": "Wife of Prophet Ibrahim (AS)",
    "origin": "Arabic",
    "verified": true
  },
  {
    "id": "ha18",
    "name": "Hajjaj",
    "gender": "Boy",
    "meaning": "Pilgrim; One who argues",
    "origin": "Arabic",
    "verified": true
  },
  {
    "id": "ha19",
    "name": "Hakam",
    "gender": "Boy",
    "meaning": "Arbitrator, judge",
    "origin": "Quranic",
    "verified": true
  },
  {
    "id": "ha20",
    "name": "Hakeem",
    "gender": "Boy",
    "meaning": "Wise, doctor",
    "origin": "Quranic",
    "verified": true
  },
  {
    "id": "ha21",
    "name": "Hala",
    "gender": "Girl",
    "meaning": "Halo around the moon",
    "origin": "Arabic",
    "verified": true
  },
  {
    "name": "Halab",
    "gender": "Boy",
    "meaning": "Aleppo (City in Syria)",
    "origin": "Arabic",
    "id": "ha101",
    "verified": true
  },
  {
    "id": "ha81",
    "name": "Halah",
    "gender": "Girl",
    "meaning": "Aureole",
    "origin": "Arabic",
    "verified": true
  },
  {
    "id": "ha22",
    "name": "Halim",
    "gender": "Boy",
    "meaning": "Gentle, patient",
    "origin": "Quranic",
    "verified": true
  },
  {
    "id": "ha23",
    "name": "Halima",
    "gender": "Girl",
    "meaning": "Gentle, patient; Prophet's wet nurse",
    "origin": "Arabic",
    "verified": true
  },
  {
    "id": "ha82",
    "name": "Halimah",
    "gender": "Girl",
    "meaning": "Gentle, patient, mild-tempered",
    "origin": "Arabic",
    "verified": true
  },
  {
    "id": "ha24",
    "name": "Hamad",
    "gender": "Boy",
    "meaning": "Praised, commendable",
    "origin": "Arabic",
    "verified": true
  },
  {
    "name": "Hamama",
    "gender": "Girl",
    "meaning": "Dove",
    "origin": "Arabic",
    "id": "ha102",
    "verified": true
  },
  {
    "id": "ha83",
    "name": "Hamamah",
    "gender": "Girl",
    "meaning": "One of the narrators of Hadith",
    "origin": "Arabic",
    "verified": true
  },
  {
    "id": "ha25",
    "name": "Hamdan",
    "gender": "Boy",
    "meaning": "The praised one",
    "origin": "Arabic",
    "verified": true
  },
  {
    "id": "ha26",
    "name": "Hamdi",
    "gender": "Boy",
    "meaning": "Of praise",
    "origin": "Arabic",
    "verified": true
  },
  {
    "id": "ha84",
    "name": "Hamdiyah",
    "gender": "Girl",
    "meaning": "One who praises a lot",
    "origin": "Arabic",
    "verified": true
  },
  {
    "id": "ha27",
    "name": "Hameeda",
    "gender": "Girl",
    "meaning": "Praiseworthy",
    "origin": "Arabic",
    "verified": true
  },
  {
    "id": "ha85",
    "name": "Hameeda",
    "gender": "Girl",
    "meaning": "Praiseworthy",
    "origin": "Arabic",
    "verified": true
  },
  {
    "id": "ha28",
    "name": "Hamid",
    "gender": "Boy",
    "meaning": "Praising (God), praiseworthy",
    "origin": "Quranic",
    "verified": true
  },
  {
    "id": "ha86",
    "name": "Hamidah",
    "gender": "Girl",
    "meaning": "Praising Allah, appreciative",
    "origin": "Arabic",
    "verified": true
  },
  {
    "id": "ha29",
    "name": "Hammad",
    "gender": "Boy",
    "meaning": "One who praises much",
    "origin": "Arabic",
    "verified": true
  },
  {
    "id": "ha30",
    "name": "Hamnah",
    "gender": "Girl",
    "meaning": "A grape; Name of a Sahabiyyah",
    "origin": "Arabic",
    "verified": true
  },
  {
    "id": "ha31",
    "name": "Hamra",
    "gender": "Girl",
    "meaning": "Red",
    "origin": "Arabic",
    "verified": true
  },
  {
    "id": "ha32",
    "name": "Hamza",
    "gender": "Boy",
    "meaning": "Lion; Strong; Uncle of the Prophet",
    "origin": "Arabic",
    "verified": true
  },
  {
    "id": "ha33",
    "name": "Hana",
    "gender": "Girl",
    "meaning": "Happiness, bliss",
    "origin": "Arabic",
    "verified": true
  },
  {
    "id": "ha87",
    "name": "Hana",
    "gender": "Girl",
    "meaning": "Happiness",
    "origin": "Arabic",
    "verified": true
  },
  {
    "id": "ha34",
    "name": "Hanan",
    "gender": "Unisex",
    "meaning": "Compassion, affection, tenderness",
    "origin": "Quranic",
    "verified": true
  },
  {
    "id": "ha88",
    "name": "Hanan",
    "gender": "Girl",
    "meaning": "Mercy",
    "origin": "Arabic",
    "verified": true
  },
  {
    "id": "ha35",
    "name": "Haneef",
    "gender": "Boy",
    "meaning": "True believer, monotheist",
    "origin": "Quranic",
    "verified": true
  },
  {
    "id": "ha89",
    "name": "Haneefah",
    "gender": "Girl",
    "meaning": "True believer",
    "origin": "Arabic",
    "verified": true
  },
  {
    "id": "ha36",
    "name": "Hani",
    "gender": "Boy",
    "meaning": "Happy, delighted",
    "origin": "Arabic",
    "verified": true
  },
  {
    "id": "ha37",
    "name": "Hania",
    "gender": "Girl",
    "meaning": "Happy, pleasant",
    "origin": "Arabic",
    "verified": true
  },
  {
    "id": "ha38",
    "name": "Hanifa",
    "gender": "Girl",
    "meaning": "True believer",
    "origin": "Arabic",
    "verified": true
  },
  {
    "id": "ha39",
    "name": "Hanin",
    "gender": "Girl",
    "meaning": "Longing, yearning",
    "origin": "Arabic",
    "verified": true
  },
  {
    "id": "ha40",
    "name": "Haniya",
    "gender": "Girl",
    "meaning": "Pleasant, happy",
    "origin": "Arabic",
    "verified": true
  },
  {
    "id": "ha90",
    "name": "Haniyyah",
    "gender": "Girl",
    "meaning": "Pleased, happy",
    "origin": "Arabic",
    "verified": true
  },
  {
    "id": "ha41",
    "name": "Hanna",
    "gender": "Girl",
    "meaning": "Compassion",
    "origin": "Arabic",
    "verified": true
  },
  {
    "id": "ha42",
    "name": "Hanzala",
    "gender": "Boy",
    "meaning": "Pond; Name of a Sahabi",
    "origin": "Arabic",
    "verified": true
  },
  {
    "id": "ha43",
    "name": "Haq",
    "gender": "Boy",
    "meaning": "Truth",
    "origin": "Quranic",
    "verified": true
  },
  {
    "name": "Haram",
    "gender": "Boy",
    "meaning": "Sanctuary (Masjid al-Haram)",
    "origin": "Arabic",
    "id": "ha103",
    "verified": true
  },
  {
    "name": "Hareer",
    "gender": "Girl",
    "meaning": "Silk",
    "origin": "Arabic",
    "id": "ha104",
    "verified": true
  },
  {
    "id": "ha44",
    "name": "Haris",
    "gender": "Boy",
    "meaning": "Guardian, cultivator",
    "origin": "Arabic",
    "verified": true
  },
  {
    "id": "ha45",
    "name": "Harith",
    "gender": "Boy",
    "meaning": "Cultivator, plowman",
    "origin": "Arabic",
    "verified": true
  },
  {
    "id": "ha46",
    "name": "Haroon",
    "gender": "Boy",
    "meaning": "Prophet Aaron",
    "origin": "Quranic",
    "verified": true
  },
  {
    "id": "ha47",
    "name": "Harun",
    "gender": "Boy",
    "meaning": "Prophet Aaron",
    "origin": "Quranic",
    "verified": true
  },
  {
    "id": "ha48",
    "name": "Hasan",
    "gender": "Boy",
    "meaning": "Handsome, good; Grandson of Prophet",
    "origin": "Arabic",
    "verified": true
  },
  {
    "id": "ha49",
    "name": "Hasanat",
    "gender": "Unisex",
    "meaning": "Good deeds",
    "origin": "Quranic",
    "verified": true
  },
  {
    "name": "Hasba",
    "gender": "Girl",
    "meaning": "Pebbles",
    "origin": "Arabic",
    "id": "ha105",
    "verified": true
  },
  {
    "id": "ha50",
    "name": "Hashem",
    "gender": "Boy",
    "meaning": "Breaker (of bread); Generous",
    "origin": "Arabic",
    "verified": true
  },
  {
    "id": "ha51",
    "name": "Hashim",
    "gender": "Boy",
    "meaning": "Crusher (of evil); Great grandfather of Prophet",
    "origin": "Arabic",
    "verified": true
  },
  {
    "id": "ha52",
    "name": "Hasib",
    "gender": "Boy",
    "meaning": "Noble, respected, calculator",
    "origin": "Quranic",
    "verified": true
  },
  {
    "id": "ha53",
    "name": "Hasin",
    "gender": "Boy",
    "meaning": "Handsome",
    "origin": "Arabic",
    "verified": true
  },
  {
    "id": "ha54",
    "name": "Hasina",
    "gender": "Girl",
    "meaning": "Beautiful, pretty",
    "origin": "Arabic",
    "verified": true
  },
  {
    "id": "ha91",
    "name": "Hasinah",
    "gender": "Girl",
    "meaning": "Pretty, beautiful",
    "origin": "Arabic",
    "verified": true
  },
  {
    "id": "ha55",
    "name": "Hasna",
    "gender": "Girl",
    "meaning": "Beautiful woman",
    "origin": "Arabic",
    "verified": true
  },
  {
    "id": "ha56",
    "name": "Hassan",
    "gender": "Boy",
    "meaning": "Very handsome, good",
    "origin": "Quranic",
    "verified": true
  },
  {
    "id": "ha57",
    "name": "Hatem",
    "gender": "Boy",
    "meaning": "Decisive, judge",
    "origin": "Arabic",
    "verified": true
  },
  {
    "id": "ha58",
    "name": "Hatib",
    "gender": "Boy",
    "meaning": "Wood collector; A Sahabi",
    "origin": "Arabic",
    "verified": true
  },
  {
    "id": "ha59",
    "name": "Hatim",
    "gender": "Boy",
    "meaning": "Judge, inevitable",
    "origin": "Arabic",
    "verified": true
  },
  {
    "name": "Haur",
    "gender": "Girl",
    "meaning": "Poplar tree",
    "origin": "Arabic",
    "id": "ha106",
    "verified": true
  },
  {
    "id": "ha92",
    "name": "Havva",
    "gender": "Girl",
    "meaning": "Eve",
    "origin": "Arabic",
    "verified": true
  },
  {
    "id": "ha60",
    "name": "Hawa",
    "gender": "Girl",
    "meaning": "Eve; Life, desire",
    "origin": "Quranic",
    "verified": true
  },
  {
    "id": "ha61",
    "name": "Hawra",
    "gender": "Girl",
    "meaning": "Woman with bright eyes (Hoor)",
    "origin": "Arabic",
    "verified": true
  },
  {
    "id": "ha62",
    "name": "Hawwa",
    "gender": "Girl",
    "meaning": "Eve",
    "origin": "Arabic",
    "verified": true
  },
  {
    "id": "ha93",
    "name": "Hawwa",
    "gender": "Girl",
    "meaning": "Eve",
    "origin": "Arabic",
    "verified": true
  },
  {
    "id": "ha63",
    "name": "Haya",
    "gender": "Girl",
    "meaning": "Modesty, shyness",
    "origin": "Arabic",
    "verified": true
  },
  {
    "id": "ha94",
    "name": "Hayah",
    "gender": "Girl",
    "meaning": "Life",
    "origin": "Arabic",
    "verified": true
  },
  {
    "id": "ha64",
    "name": "Hayam",
    "gender": "Girl",
    "meaning": "Deliriously in love",
    "origin": "Arabic",
    "verified": true
  },
  {
    "id": "ha95",
    "name": "Hayam",
    "gender": "Girl",
    "meaning": "Deliriously in love",
    "origin": "Arabic",
    "verified": true
  },
  {
    "id": "ha65",
    "name": "Hayat",
    "gender": "Girl",
    "meaning": "Life",
    "origin": "Quranic",
    "verified": true
  },
  {
    "id": "ha96",
    "name": "Hayat",
    "gender": "Girl",
    "meaning": "Life",
    "origin": "Arabic",
    "verified": true
  },
  {
    "id": "ha66",
    "name": "Haydar",
    "gender": "Boy",
    "meaning": "Lion",
    "origin": "Arabic",
    "verified": true
  },
  {
    "id": "ha67",
    "name": "Haytham",
    "gender": "Boy",
    "meaning": "Young eagle",
    "origin": "Arabic",
    "verified": true
  },
  {
    "name": "Hazan",
    "gender": "Girl",
    "meaning": "Autumn",
    "origin": "Turkish",
    "id": "ha107",
    "verified": true
  },
  {
    "id": "ha68",
    "name": "Hazem",
    "gender": "Boy",
    "meaning": "Firm, resolute",
    "origin": "Arabic",
    "verified": true
  },
  {
    "id": "ha69",
    "name": "Hazim",
    "gender": "Boy",
    "meaning": "Determined, firm",
    "origin": "Arabic",
    "verified": true
  },
  {
    "id": "ha70",
    "name": "Hazina",
    "gender": "Girl",
    "meaning": "Autumn, treasure",
    "origin": "Arabic",
    "verified": true
  },
  {
    "id": "ha97",
    "name": "Haziq",
    "gender": "Boy",
    "meaning": "Intelligent, skillful",
    "origin": "Arabic",
    "verified": true
  },
  {
    "id": "ha98",
    "name": "Haziqah",
    "gender": "Girl",
    "meaning": "Clever, intelligent",
    "origin": "Arabic",
    "verified": true
  },
  {
    "id": "ha99",
    "name": "Hazirah",
    "gender": "Girl",
    "meaning": "Clean",
    "origin": "Arabic",
    "verified": true
  },
  {
    "id": "ha100",
    "name": "Hazzah",
    "gender": "Girl",
    "meaning": "Lucky",
    "origin": "Arabic",
    "verified": true
  }
]