[
  {
    "name": "Osaid",
    "gender": "Boy",
    "meaning": "Little lion",
    "origin": "Arabic",
    "id": "os1",
    "verified": true
  },
  {
    "name": "Osaida",
    "gender": "Girl",
    "meaning": "Little lioness",
    "origin": "Arabic",
    "id": "os2",
    "verified": true
  },
  {
    "name": "Osaidah",
    "gender": "Girl",
    "meaning": "Little lioness",
    "origin": "Arabic",
    "id": "os3",
    "verified": true
  },
  {
    "name": "Osaima",
    "gender": "Girl",
    "meaning": "Little lioness",
    "origin": "Arabic",
    "id": "os4",
    "verified": true
  },
  {
    "name": "Osaimah",
    "gender": "Girl",
    "meaning": "Little lioness",
    "origin": "Arabic",
    "id": "os5",
    "verified": true
  },
  {
    "name": "Osaman",
    "gender": "Boy",
    "meaning": "Baby lion",
    "origin": "Arabic",
    "id": "os6",
    "verified": true
  },
  {
    "name": "Osamayah",
    "gender": "Girl",
    "meaning": "Pertaining to a lion",
    "origin": "Arabic",
    "id": "os7",
    "verified": true
  },
  {
    "name": "Osameh",
    "gender": "Boy",
    "meaning": "Lion",
    "origin": "Arabic",
    "id": "os8",
    "verified": true
  },
  {
    "name": "Oshae",
    "gender": "Boy",
    "meaning": "A Prophet's companion",
    "origin": "Arabic",
    "id": "os9",
    "verified": true
  },
  {
    "name": "Osheen",
    "gender": "Girl",
    "meaning": "Shining, beautiful",
    "origin": "Persian",
    "id": "os10",
    "verified": true
  },
  {
    "name": "Osma",
    "gender": "Girl",
    "meaning": "Baby lioness",
    "origin": "Arabic",
    "id": "os11",
    "verified": true
  },
  {
    "name": "Osmana",
    "gender": "Girl",
    "meaning": "Baby bustard bird",
    "origin": "Arabic",
    "id": "os12",
    "verified": true
  },
  {
    "name": "Osmani",
    "gender": "Boy",
    "meaning": "Pertaining to Osman",
    "origin": "Arabic",
    "id": "os13",
    "verified": true
  },
  {
    "name": "Osmaniya",
    "gender": "Girl",
    "meaning": "Pertaining to Osman",
    "origin": "Arabic",
    "id": "os14",
    "verified": true
  },
  {
    "name": "Osmaniyah",
    "gender": "Girl",
    "meaning": "Pertaining to Osman",
    "origin": "Arabic",
    "id": "os15",
    "verified": true
  },
  {
    "name": "Osmany",
    "gender": "Boy",
    "meaning": "Pertaining to Osman",
    "origin": "Arabic",
    "id": "os16",
    "verified": true
  },
  {
    "name": "Osmanyah",
    "gender": "Girl",
    "meaning": "Pertaining to Osman",
    "origin": "Arabic",
    "id": "os17",
    "verified": true
  },
  {
    "name": "Osmanyia",
    "gender": "Girl",
    "meaning": "Pertaining to Osman",
    "origin": "Arabic",
    "id": "os18",
    "verified": true
  },
  {
    "name": "Ossama",
    "gender": "Boy",
    "meaning": "Lion",
    "origin": "Arabic",
    "id": "os19",
    "verified": true
  }
]