[
  {
    "name": "Pinar",
    "gender": "Girl",
    "meaning": "Spring, fountain",
    "origin": "Turkish",
    "id": "pi4",
    "verified": true
  },
  {
    "id": "pi1",
    "name": "Pir",
    "gender": "Boy",
    "meaning": "Elder, Saint, Spiritual Guide",
    "origin": "Persian",
    "verified": true
  },
  {
    "id": "pi2",
    "name": "Pirouz",
    "gender": "Boy",
    "meaning": "Victorious",
    "origin": "Persian",
    "verified": true
  },
  {
    "id": "pi3",
    "name": "Pirzada",
    "gender": "Boy",
    "meaning": "Son of a Saint",
    "origin": "Persian",
    "verified": true
  }
]