[
  {
    "name": "Udad",
    "gender": "Boy",
    "meaning": "Affection",
    "origin": "Arabic",
    "id": "ud3",
    "verified": true
  },
  {
    "name": "Uday",
    "gender": "Boy",
    "meaning": "One who runs fast",
    "origin": "Arabic",
    "id": "ud1",
    "verified": true
  },
  {
    "name": "Udayl",
    "gender": "Boy",
    "meaning": "Just",
    "origin": "Arabic",
    "id": "ud4",
    "verified": true
  },
  {
    "name": "Udays",
    "gender": "Boy",
    "meaning": "Small runner",
    "origin": "Arabic",
    "id": "ud2",
    "verified": true
  }
]